tenses_py/__init__.py
tenses_py-0.0.1.dist-info/LICENSE
tenses_py-0.0.1.dist-info/METADATA
tenses_py-0.0.1.dist-info/WHEEL
tenses_py-0.0.1.dist-info/top_level.txt
tenses_py-0.0.1.dist-info/RECORD
